youtube_synopsis/__init__.py
youtube_synopsis/youtube_synopsis.py
youtube_synopsis-1.0.0.dist-info/METADATA
youtube_synopsis-1.0.0.dist-info/WHEEL
youtube_synopsis-1.0.0.dist-info/top_level.txt
youtube_synopsis-1.0.0.dist-info/RECORD
